mcp_ntopng/__init__.py
mcp_ntopng/main.py
mcp_ntopng/mcp_config.py
mcp_ntopng/mcp_server.py
mcp_ntopng/ntopng_schema.py
mseep_mcp_ntopng-0.1.1.dist-info/licenses/LICENSE
mseep_mcp_ntopng-0.1.1.dist-info/METADATA
mseep_mcp_ntopng-0.1.1.dist-info/WHEEL
mseep_mcp_ntopng-0.1.1.dist-info/entry_points.txt
mseep_mcp_ntopng-0.1.1.dist-info/top_level.txt
mseep_mcp_ntopng-0.1.1.dist-info/RECORD
